cidc_schemas/__init__.py
cidc_schemas/cli.py
cidc_schemas/constants.py
cidc_schemas/json_validation.py
cidc_schemas/migrations.py
cidc_schemas/template.py
cidc_schemas/template_reader.py
cidc_schemas/template_writer.py
cidc_schemas/unprism.py
cidc_schemas/util.py
cidc_schemas/metaschema/strict_meta_schema.json
cidc_schemas/ngs_pipeline_api/__init__.py
cidc_schemas/ngs_pipeline_api/output_API.schema.json
cidc_schemas/ngs_pipeline_api/atacseq/atacseq.md
cidc_schemas/ngs_pipeline_api/atacseq/atacseq_output_API.json
cidc_schemas/ngs_pipeline_api/atacseq/imgs/atacseq.png
cidc_schemas/ngs_pipeline_api/rna/rna.md
cidc_schemas/ngs_pipeline_api/rna/rna_config.schema.json
cidc_schemas/ngs_pipeline_api/rna/rna_output_API.json
cidc_schemas/ngs_pipeline_api/rna/imgs/RIMA.png
cidc_schemas/ngs_pipeline_api/tcr/tcr.md
cidc_schemas/ngs_pipeline_api/tcr/imgs/TCRseq.png
cidc_schemas/ngs_pipeline_api/wes/wes.md
cidc_schemas/ngs_pipeline_api/wes/wes_config.schema.json
cidc_schemas/ngs_pipeline_api/wes/wes_output_API.json
cidc_schemas/ngs_pipeline_api/wes/wes_output_API.py
cidc_schemas/ngs_pipeline_api/wes/wes_tumor_only_output_API.json
cidc_schemas/ngs_pipeline_api/wes/imgs/wes.png
cidc_schemas/pipeline_configs/rna_level1_analysis_config.yaml.j2
cidc_schemas/prism/__init__.py
cidc_schemas/prism/constants.py
cidc_schemas/prism/core.py
cidc_schemas/prism/extra_metadata.py
cidc_schemas/prism/merger.py
cidc_schemas/prism/pipelines.py
cidc_schemas/schemas/aliquot.json
cidc_schemas/schemas/clinical_data.json
cidc_schemas/schemas/clinical_trial.json
cidc_schemas/schemas/participant.json
cidc_schemas/schemas/sample.json
cidc_schemas/schemas/shipping_core.json
cidc_schemas/schemas/artifacts/artifact_bam.json
cidc_schemas/schemas/artifacts/artifact_bam_bai.json
cidc_schemas/schemas/artifacts/artifact_bed.json
cidc_schemas/schemas/artifacts/artifact_bigwig.json
cidc_schemas/schemas/artifacts/artifact_binary.json
cidc_schemas/schemas/artifacts/artifact_clinical_csv.json
nci_cidc_schemas-0.28.12.dist-info/licenses/LICENSE
nci_cidc_schemas-0.28.12.dist-info/METADATA
nci_cidc_schemas-0.28.12.dist-info/WHEEL
nci_cidc_schemas-0.28.12.dist-info/entry_points.txt
nci_cidc_schemas-0.28.12.dist-info/top_level.txt
nci_cidc_schemas-0.28.12.dist-info/RECORD
