Metadata-Version: 2.4
Name: nci_cidc_schemas
Version: 0.28.12
Summary: The CIDC data model and tools for working with it.
Home-page: https://github.com/NCI-CIDC/cidc-schemas
Author: NCI
Author-email: nci-cidc-tools-admin@mail.nih.gov
License: MIT license
Keywords: cidc_schemas
Classifier: Development Status :: 2 - Pre-Alpha
Classifier: Intended Audience :: Developers
Classifier: License :: OSI Approved :: MIT License
Classifier: Natural Language :: English
Classifier: Programming Language :: Python :: 3.13
Requires-Python: >=3.13,<3.14
License-File: LICENSE
Requires-Dist: argparse==1.4.0
Requires-Dist: dateparser==1.2.2
Requires-Dist: deepdiff==8.6.1
Requires-Dist: jinja2==3.1.6
Requires-Dist: jsonmerge==1.6.1
Requires-Dist: jsonpointer==3.0.0
Requires-Dist: jsonschema==3.2.0
Requires-Dist: openpyxl==3.1.5
Requires-Dist: pandas==2.3.3
Requires-Dist: pyyaml==6.0.3
Requires-Dist: xlsxwriter==3.2.9
Dynamic: author
Dynamic: author-email
Dynamic: classifier
Dynamic: description
Dynamic: description-content-type
Dynamic: home-page
Dynamic: keywords
Dynamic: license
Dynamic: license-file
Dynamic: requires-dist
Dynamic: requires-python
Dynamic: summary
